README.md
setup.py
skltools/__init__.py
skltools/tools.py
skltools/xgbc.py
skltools.egg-info/PKG-INFO
skltools.egg-info/SOURCES.txt
skltools.egg-info/dependency_links.txt
skltools.egg-info/top_level.txt