Metadata-Version: 2.1
Name: skltools
Version: 0.0.3
Summary: for scikit-learn package
Home-page: https://gitee.com/znuel_quant/skltools
Author: zuel_quant_tools
Author-email: 18981453250@163.com
License: UNKNOWN
Platform: UNKNOWN
Classifier: Programming Language :: Python :: 3
Classifier: License :: OSI Approved :: MIT License
Classifier: Operating System :: OS Independent
Requires-Python: >=3.6
